django_cheroot/__init__.py
django_cheroot/admin.py
django_cheroot/apps.py
django_cheroot/management/__init__.py
django_cheroot/management/commands/__init__.py
django_cheroot/management/commands/cheroot.py
django_cheroot-1.0.2.dist-info/LICENSE
django_cheroot-1.0.2.dist-info/METADATA
django_cheroot-1.0.2.dist-info/WHEEL
django_cheroot-1.0.2.dist-info/top_level.txt
django_cheroot-1.0.2.dist-info/RECORD
