Metadata-Version: 2.1
Name: django-cheroot
Version: 1.0.2
Summary: Django Cheroot provides a bridge to use Cheroot which is the high-performance, pure-Python HTTP server used by CherryPy
Home-page: https://github.com/modbender/django-cheroot
Author: Yashas H R
Author-email: rameshmamathayashas@gmail.com
Platform: any
Classifier: Environment :: Web Environment
Classifier: Framework :: Django
Classifier: Intended Audience :: Developers
Classifier: Operating System :: OS Independent
Classifier: Programming Language :: Python
Classifier: Programming Language :: Python :: 3
Classifier: Programming Language :: Python :: 3 :: Only
Classifier: Topic :: Software Development :: Libraries :: Python Modules
Requires-Python: >=3.5
License-File: LICENSE
Requires-Dist: django (>=2.2.24)
Requires-Dist: cheroot (>=8.2.1)
